whisperx_api/__init__.py
whisperx_api/__main__.py
whisperx_api/auth.py
whisperx_api/config.py
whisperx_api/database.py
whisperx_api/deps.py
whisperx_api/main.py
whisperx_api/model_manager.py
whisperx_api/models.py
whisperx_api/server.py
whisperx_api/transcriber.py
whisperx_api-2.0.1rc2.dist-info/METADATA
whisperx_api-2.0.1rc2.dist-info/WHEEL
whisperx_api-2.0.1rc2.dist-info/entry_points.txt
whisperx_api-2.0.1rc2.dist-info/licenses/LICENSE
whisperx_api-2.0.1rc2.dist-info/RECORD
