Metadata-Version: 2.4
Name: whisperx-api
Version: 2.0.1rc2
Summary: Local WhisperX transcription API with speaker diarization
Project-URL: Homepage, https://github.com/namastexlabs/whisperx-api
Project-URL: Repository, https://github.com/namastexlabs/whisperx-api.git
Project-URL: Issues, https://github.com/namastexlabs/whisperx-api/issues
Author: namastexlabs
License: MIT
License-File: LICENSE
Keywords: api,speech-to-text,transcription,whisper,whisperx
Classifier: Development Status :: 4 - Beta
Classifier: Environment :: GPU :: NVIDIA CUDA
Classifier: Framework :: FastAPI
Classifier: License :: OSI Approved :: MIT License
Classifier: Operating System :: OS Independent
Classifier: Programming Language :: Python :: 3.12
Classifier: Topic :: Multimedia :: Sound/Audio :: Speech
Requires-Python: <3.13,>=3.12
Requires-Dist: aiosqlite>=0.19
Requires-Dist: fastapi>=0.100
Requires-Dist: httpx>=0.25
Requires-Dist: imageio-ffmpeg>=0.4.9
Requires-Dist: omegaconf>=2.3.0
Requires-Dist: pyannote-audio>=4.0
Requires-Dist: pydantic-settings>=2.0
Requires-Dist: pydantic>=2.0
Requires-Dist: python-dotenv>=1.0
Requires-Dist: python-multipart>=0.0.6
Requires-Dist: speechbrain>=1.0
Requires-Dist: torch>=2.9.0
Requires-Dist: torchaudio>=2.8.0
Requires-Dist: torchvision>=0.24.1
Requires-Dist: uvicorn>=0.20
Requires-Dist: whisperx>=3.1.1
Provides-Extra: dev
Requires-Dist: mypy>=1.0; extra == 'dev'
Requires-Dist: pytest-asyncio>=0.21; extra == 'dev'
Requires-Dist: pytest>=7.0; extra == 'dev'
Requires-Dist: ruff>=0.1; extra == 'dev'
